src/__init__.py
aptos_python_sdk-0.0.1.dist-info/METADATA
aptos_python_sdk-0.0.1.dist-info/WHEEL
aptos_python_sdk-0.0.1.dist-info/licenses/LICENSE
aptos_python_sdk-0.0.1.dist-info/RECORD
